WeiFuwuJiagouWenji/README.md
WeiFuwuJiagouWenji/__init__.py
WeiFuwuJiagouWenji/__main__.py
WeiFuwuJiagouWenji/file.epub
WeiFuwuJiagouWenji/index.html
WeiFuwuJiagouWenji/css/__init__.py
WeiFuwuJiagouWenji/css/annotations.css
WeiFuwuJiagouWenji/css/main.css
WeiFuwuJiagouWenji/css/normalize.css
WeiFuwuJiagouWenji/css/popup.css
WeiFuwuJiagouWenji/font/__init__.py
WeiFuwuJiagouWenji/font/fontello.eot
WeiFuwuJiagouWenji/font/fontello.svg
WeiFuwuJiagouWenji/font/fontello.ttf
WeiFuwuJiagouWenji/font/fontello.woff
WeiFuwuJiagouWenji/img/__init__.py
WeiFuwuJiagouWenji/img/annotator-glyph-sprite.png
WeiFuwuJiagouWenji/img/annotator-icon-sprite.png
WeiFuwuJiagouWenji/img/apple-touch-icon.png
WeiFuwuJiagouWenji/img/cancelfullscreen.png
WeiFuwuJiagouWenji/img/close.png
WeiFuwuJiagouWenji/img/fullscreen.png
WeiFuwuJiagouWenji/img/loader.gif
WeiFuwuJiagouWenji/img/menu-icon.png
WeiFuwuJiagouWenji/img/save.png
WeiFuwuJiagouWenji/img/saved.png
WeiFuwuJiagouWenji/img/settings-s.png
WeiFuwuJiagouWenji/img/settings.png
WeiFuwuJiagouWenji/img/star.png
WeiFuwuJiagouWenji/js/__init__.py
WeiFuwuJiagouWenji/js/epub.js
WeiFuwuJiagouWenji/js/epub.min.js
WeiFuwuJiagouWenji/js/epub.min.map
WeiFuwuJiagouWenji/js/hooks.min.js
WeiFuwuJiagouWenji/js/hooks.min.map
WeiFuwuJiagouWenji/js/reader.js
WeiFuwuJiagouWenji/js/reader.js.map
WeiFuwuJiagouWenji/js/reader.min.js
WeiFuwuJiagouWenji/js/reader.min.map
WeiFuwuJiagouWenji/js/hooks/__init__.py
WeiFuwuJiagouWenji/js/hooks/extensions/__init__.py
WeiFuwuJiagouWenji/js/hooks/extensions/highlight.js
WeiFuwuJiagouWenji/js/libs/__init__.py
WeiFuwuJiagouWenji/js/libs/jquery.min.js
WeiFuwuJiagouWenji/js/libs/localforage.min.js
WeiFuwuJiagouWenji/js/libs/screenfull.js
WeiFuwuJiagouWenji/js/libs/screenfull.min.js
WeiFuwuJiagouWenji/js/libs/zip.min.js
WeiFuwuJiagouWenji/js/plugins/__init__.py
WeiFuwuJiagouWenji/js/plugins/hypothesis.js
WeiFuwuJiagouWenji/js/plugins/search.js
wei_fuwu_jiagou_wenji-2024.2.29.0.dist-info/METADATA
wei_fuwu_jiagou_wenji-2024.2.29.0.dist-info/WHEEL
wei_fuwu_jiagou_wenji-2024.2.29.0.dist-info/entry_points.txt
wei_fuwu_jiagou_wenji-2024.2.29.0.dist-info/top_level.txt
wei_fuwu_jiagou_wenji-2024.2.29.0.dist-info/RECORD
